{
  "name": "收容舱段-1",
  "author": "Souloco",
  "start": [
    {
      "map": "2"
    },
    {
      "map_1-2_point_2.jpg": 1.5
    },
    {
      "transfer": 1.5
    }
  ],
  "map": [
    {
      "s": 0.4868850999998813
    },
    {
      "fighting": 3
    },
    {
      "s": 3.8470121999998355
    },
    {
      "e": 1
    },
    {
      "fighting": 1
    },
    {
      "s": 0.3121110000000044
    },
    {
      "a": 1.2399420000001555
    },
    {
      "w": 0.8919852999999875
    },
    {
      "a": 2.222756299999901
    },
    {
      "w": 4.917057500000055
    },
    {
      "a": 1.493931400000065
    },
    {
      "s": 1.3129378000000543
    },
    {
      "a": 0.7650008999999045
    },
    {
      "s": 2.7228913000000375
    },
    {
      "e": 1
    },
    {
      "fighting": 1
    }
  ]
}