{
  "name": "铁卫禁区-1",
  "author": "Souloco",
  "start": [
    {
      "map": ""
    },
    {
      "map_2-0_point_1.jpg": 1.5
    },
    {
      "transfer": 1.5
    }
  ],
  "map": [
    {
      "E":[3,"s"]
    },
    {
      "E":[1,"a"]
    },
    {
      "E":[2,"s"]
    },
    {
      "E":[1,"d"]
    },
    {
      "E":[7,"s"]
    },
    {
      "E":[2,"a"]
    },
    {
      "E":[1,"w"]
    },
    {
      "E":[3,"a"]
    },
    {
      "E":[1,"s"]
    },
    {
      "E":[3,"a"]
    },
    {
      "E":[1,"w"]
    }
  ]
}