{
  "name": "边缘通路-2", 
  "author": "Souloco", 
  "start": [ 
      {"map": ""}, 
      {"map_2-2_point_1.jpg": 1.5}, 
      {"transfer": 1.5} 
  ], 
  "map": [
    {
      "s": 6.0358487999939825
    },
    {
      "d": 1.352139799995348
    },
    {
      "fighting": 1
    },
    {
      "fighting": 2
    },
    {
      "d": 3.452139799995348
    },
    {
      "fighting": 2
    },
    {
      "fighting": 1
    },

    {
      "d": 1.5310809000016889
    },
    {
      "fighting": 1
    },
    {
      "d": 3.5001380000903741
    },
    {
      "w": 1.0003432323233212
    },
    {
      "a": 1.0169079999992391
    },
    {
      "w": 2.583170700012124
    },
    {
      "fighting": 1
    },
    {
      "d": 4.864886599994497
    },
    {
      "s": 1.4769136999937473
    },
    {
      "d": 5.1699443999968935
    },
    {
      "fighting": 1
    },
    {
      "d": 1.168926299989107
    },
    {
      "fighting": 2
    },
    {
      "d": 2.68926299989107
    },
    {
      "delay": 0.7
    },
    {
      "a": 0.91892629998910
    },
    {
      "w": 1.01892629998910
    },
    {
      "fighting": 1
    }
  ]
}