{
    "name": "流云渡-5",
    "author": "Souloco",
    "start": [
        {"map": "1"},
        {"map_3-1_point_3.png": 1.5},
        {"transfer": 1.5}
    ],
  "map": [
    {
      "d": 6.604721200002823
    },
    {
      "s": 1.506316600011196
    },
    {
      "e": 1
    },
    {
      "fighting": 1
    },
    {
      "s": 2.6789473999931943
    },
    {
      "a": 0.8623185000033118
    },
    {
      "e": 1
    },
    {
      "fighting": 1
    },
    {
      "s": 1.5789473999931943
    },
    {
      "e": 1
    },
    {
      "fighting": 1
    }
  ]
}